Metadata-Version: 1.0
Name: infosearch
Version: 1.0
Summary: python search api by tornado
Home-page: https://github.com/jiangsir404
Author: rivir
Author-email: rivirsec@163.com
License: UNKNOWN
Platform: UNKNOWN
